Katna/__init__.py
Katna/config.py
Katna/crop_extractor.py
Katna/crop_rect.py
Katna/crop_selector.py
Katna/decorators.py
Katna/exceptions.py
Katna/feature_list.py
Katna/filter_list.py
Katna/frame_extractor.py
Katna/helper_functions.py
Katna/image.py
Katna/image_selector.py
Katna/mediapipe.py
Katna/version.py
Katna/video.py
Katna/video_compressor.py
Katna/writer.py
Katna/image_features/__init__.py
Katna/image_features/edge_feature.py
Katna/image_features/face_feature.py
Katna/image_features/feature.py
Katna/image_features/saliency_feature.py
Katna/image_filters/__init__.py
Katna/image_filters/filter.py
Katna/image_filters/text_detector.py
tests/__init__.py
tests/image_similarity.py
tests/test_all_video.py
tests/test_image.py
katna-0.9.2.dist-info/LICENSE.txt
katna-0.9.2.dist-info/METADATA
katna-0.9.2.dist-info/WHEEL
katna-0.9.2.dist-info/top_level.txt
katna-0.9.2.dist-info/RECORD
