Metadata-Version: 2.1
Name: katna
Version: 0.9.2
Summary: Katna is a tool that automates video key/best frames extraction.
Home-page: https://github.com/keplerlab/Katna.git
Author: keplerlab
Author-email: keplerwaasi@gmail.com
License: UNKNOWN
Project-URL: Documentation, https://katna.readthedocs.io
Project-URL: Source, https://github.com/keplerlab/Katna
Project-URL: Tracker, https://github.com/keplerlab/Katna/issues
Platform: UNKNOWN
Classifier: Programming Language :: Python :: 3
Classifier: License :: OSI Approved :: MIT License
Classifier: Operating System :: OS Independent
Requires-Python: >=3.6
Requires-Dist: scipy
Requires-Dist: scikit-learn
Requires-Dist: scikit-image
Requires-Dist: opencv-contrib-python (>=3.4.7)
Requires-Dist: numpy (>=1.15)
Requires-Dist: imageio-ffmpeg (>=0.2.0)
Requires-Dist: imutils
Requires-Dist: requests
Requires-Dist: psutil
Requires-Dist: ffmpy
